flytekitplugins_sqlalchemy-1.16.12-py3.14-nspkg.pth
flytekitplugins/sqlalchemy/__init__.py
flytekitplugins/sqlalchemy/task.py
flytekitplugins_sqlalchemy-1.16.12.dist-info/METADATA
flytekitplugins_sqlalchemy-1.16.12.dist-info/WHEEL
flytekitplugins_sqlalchemy-1.16.12.dist-info/namespace_packages.txt
flytekitplugins_sqlalchemy-1.16.12.dist-info/top_level.txt
flytekitplugins_sqlalchemy-1.16.12.dist-info/RECORD
